{
 "podcast-p-with-paul-george": {
  "rank": 1,
  "chart": "Comedy (US)",
  "fetchedAt": "2026-07-24"
 },
 "baby-this-is-keke-palmer": {
  "rank": 6,
  "chart": "Comedy (US)",
  "fetchedAt": "2026-07-24"
 },
 "the-read": {
  "rank": 22,
  "chart": "Comedy (US)",
  "fetchedAt": "2026-07-24"
 },
 "the-breakfast-club": {
  "rank": 26,
  "chart": "Comedy (US)",
  "fetchedAt": "2026-07-24"
 },
 "shxtsngigs": {
  "rank": 59,
  "chart": "Comedy (US)",
  "fetchedAt": "2026-07-24"
 },
 "85-south-show": {
  "rank": 126,
  "chart": "Comedy (US)",
  "fetchedAt": "2026-07-24"
 },
 "brilliant-idiots": {
  "rank": 162,
  "chart": "Comedy (US)",
  "fetchedAt": "2026-07-24"
 },
 "steve-harvey": {
  "rank": 178,
  "chart": "Comedy (US)",
  "fetchedAt": "2026-07-24"
 },
 "decisions-decisions": {
  "rank": 181,
  "chart": "Comedy (US)",
  "fetchedAt": "2026-07-24"
 },
 "the-friend-zone": {
  "rank": 188,
  "chart": "Comedy (US)",
  "fetchedAt": "2026-07-24"
 },
 "tea-with-tia": {
  "rank": 6,
  "chart": "Sports (US)",
  "fetchedAt": "2026-07-24"
 },
 "club-520-podcast": {
  "rank": 19,
  "chart": "Sports (US)",
  "fetchedAt": "2026-07-24"
 },
 "club-shay-shay": {
  "rank": 20,
  "chart": "Sports (US)",
  "fetchedAt": "2026-07-24"
 },
 "nightcap": {
  "rank": 41,
  "chart": "Sports (US)",
  "fetchedAt": "2026-07-24"
 },
 "7pm-in-brooklyn": {
  "rank": 46,
  "chart": "Sports (US)",
  "fetchedAt": "2026-07-24"
 },
 "all-the-smoke": {
  "rank": 50,
  "chart": "Sports (US)",
  "fetchedAt": "2026-07-24"
 },
 "the-joe-budden-podcast": {
  "rank": 1,
  "chart": "Music (US)",
  "fetchedAt": "2026-07-24"
 },
 "the-joe-and-jada-podcast": {
  "rank": 5,
  "chart": "Music (US)",
  "fetchedAt": "2026-07-24"
 },
 "new-rory-and-mal": {
  "rank": 8,
  "chart": "Music (US)",
  "fetchedAt": "2026-07-24"
 },
 "million-dollaz-worth-of-game": {
  "rank": 22,
  "chart": "Music (US)",
  "fetchedAt": "2026-07-24"
 },
 "red-table-talk": {
  "rank": 25,
  "chart": "Music (US)",
  "fetchedAt": "2026-07-24"
 },
 "questlove-supreme": {
  "rank": 26,
  "chart": "Music (US)",
  "fetchedAt": "2026-07-24"
 },
 "angie-martinez-irl": {
  "rank": 31,
  "chart": "Music (US)",
  "fetchedAt": "2026-07-24"
 },
 "drink-champs": {
  "rank": 32,
  "chart": "Music (US)",
  "fetchedAt": "2026-07-24"
 },
 "rb-money": {
  "rank": 55,
  "chart": "Music (US)",
  "fetchedAt": "2026-07-24"
 },
 "big-facts-big-bank-dj-scream": {
  "rank": 70,
  "chart": "Music (US)",
  "fetchedAt": "2026-07-24"
 },
 "good-moms-bad-choices": {
  "rank": 146,
  "chart": "Music (US)",
  "fetchedAt": "2026-07-24"
 },
 "rap-radar": {
  "rank": 189,
  "chart": "Music (US)",
  "fetchedAt": "2026-07-24"
 },
 "way-up-with-angela-yee": {
  "rank": 103,
  "chart": "Business (US)",
  "fetchedAt": "2026-07-24"
 },
 "brown-ambition": {
  "rank": 18,
  "chart": "Society & Culture (US)",
  "fetchedAt": "2026-07-24"
 },
 "higher-learning-van-lathan-rachel-lindsay": {
  "rank": 104,
  "chart": "Society & Culture (US)",
  "fetchedAt": "2026-07-24"
 },
 "the-jason-lee-podcast-hollywood-unlocked": {
  "rank": 135,
  "chart": "Society & Culture (US)",
  "fetchedAt": "2026-07-24"
 }
}
